flaskapi.py
setup.py
Flask_Base_API.egg-info/PKG-INFO
Flask_Base_API.egg-info/SOURCES.txt
Flask_Base_API.egg-info/dependency_links.txt
Flask_Base_API.egg-info/requires.txt
Flask_Base_API.egg-info/top_level.txt