Metadata-Version: 1.0
Name: Flask-Base-API
Version: 0.1.6
Summary: Flask的Api包，用于快速开发API接口
Home-page: https://github.com/Lzejie/Flask-API
Author: L_zejie
Author-email: lzj_xuexi@163.com
License: MIT Licence
Keywords: Flask API,API
Platform: UNKNOWN
